{
	"name": "level 2",
	"layers": [
		{
			"name": "Layer 0",
			"overriden": 0,
			"instances": [
				{
					"type": "TiledBackground3",
					"properties": {
						"initially-visible": true,
						"origin": "top-left",
						"wrap-horizontal": "repeat",
						"wrap-vertical": "repeat",
						"image-offset-x": 0,
						"image-offset-y": 0,
						"image-scale-x": 1,
						"image-scale-y": 1,
						"image-angle": 0
					},
					"uid": 9,
					"instanceVariables": {},
					"behaviors": {},
					"world": {
						"x": -5,
						"y": -43,
						"width": 983,
						"height": 543,
						"originX": 0,
						"originY": 0,
						"color": [
							1,
							1,
							1,
							1
						],
						"angle": 0,
						"zElevation": 0
					}
				},
				{
					"type": "Tilemap2",
					"properties": {
						"initially-visible": true,
						"tile-width": 16,
						"tile-height": 16,
						"tile-x-offset": 0,
						"tile-y-offset": 0,
						"tile-x-spacing": 0,
						"tile-y-spacing": 0,
						"tile-x-drawing-offset": 0,
						"tile-y-drawing-offset": 0,
						"drawing-mode": "top-to-right"
					},
					"uid": 16,
					"instanceVariables": {},
					"behaviors": {
						"Solid": {
							"properties": {
								"enabled": true,
								"tags": ""
							}
						}
					},
					"ownData": {
						"tilemapData": {
							"width": 106,
							"height": 60,
							"max-width": 106,
							"max-height": 60,
							"data": "29x0,2x64,58x0,2x64,58x0,2x64,58x0,2x64,58x0,2x64,58x0,2x64,58x0,2x64,58x0,2x64,58x0,2x64,58x0,2x64,58x0,2x64,58x0,2x64,58x0,2x64,58x0,2x64,58x0,2x64,58x0,2x64,58x0,2x64,58x0,2x64,58x0,2x64,58x0,2x64,58x0,2x64,58x0,2x64,58x0,2x64,58x0,2x64,58x0,2x64,58x0,2x64,58x0,2x64,58x0,2x64,58x0,2x64,58x0,2x64,58x0,2x64,58x0,2x64,58x0,2x64,58x0,2x64,58x0,2x64,58x0,2x64,58x0,2x64,58x0,2x64,58x0,2x64,58x0,2x64,58x0,2x64,58x0,2x64,58x0,2x64,58x0,2x64,58x0,2x64,58x0,2x64,58x0,2x64,58x0,3x64,57x0,3x64,57x0,3x64,57x0,3x64,57x0,3x64,57x0,2x64,58x0,2x64,58x0,2x64,58x0,2x64,58x0,2x64,58x0,2x64,58x0,2x64,58x0,2x64,58x0,2x64,58x0,2x64,59x0,64,2609x0"
						},
						"tile-width": 16,
						"tile-height": 16,
						"tile-x-offset": 0,
						"tile-y-offset": 0,
						"tile-x-spacing": 0,
						"tile-y-spacing": 0
					},
					"world": {
						"x": -10,
						"y": 4,
						"width": 1708,
						"height": 960,
						"originX": 0,
						"originY": 0,
						"color": [
							1,
							1,
							1,
							1
						],
						"zElevation": 0
					}
				}
			],
			"sid": 868549011880659,
			"effectTypes": [],
			"isInitiallyVisible": true,
			"color": [
				1,
				1,
				1,
				1
			],
			"backgroundColor": [
				1,
				1,
				1,
				1
			],
			"isTransparent": false,
			"parallaxX": 1,
			"parallaxY": 1,
			"scaleRate": 1,
			"forceOwnTexture": false,
			"useRenderCells": false,
			"blendMode": "normal",
			"global": false
		}
	],
	"sid": 910750430869876,
	"nonworld-instances": [],
	"effectTypes": [],
	"width": 1708,
	"height": 960,
	"unboundedScrolling": false,
	"eventSheet": "Level 2 event sheet"
}